materialize_threats/__init__.py
materialize_threats/materialize.py
materialize_threats/db/__init__.py
materialize_threats/db/dbgraph.py
materialize_threats/gherkin_stride/__init__.py
materialize_threats/gherkin_stride/gherkin_stride.py
materialize_threats/gherkin_stride/templates.py
materialize_threats/mx/__init__.py
materialize_threats/mx/io/CurveFactory.py
materialize_threats/mx/io/EdgeFactory.py
materialize_threats/mx/io/NodeFactory.py
materialize_threats/mx/io/UserObjectFactory.py
materialize_threats/mx/io/__init__.py
materialize_threats/mx/models/Curve.py
materialize_threats/mx/models/Edge.py
materialize_threats/mx/models/GraphObj.py
materialize_threats/mx/models/LinearRegression.py
materialize_threats/mx/models/MxGraph.py
materialize_threats/mx/models/Node.py
materialize_threats/mx/models/Shape.py
materialize_threats/mx/models/Styles.py
materialize_threats/mx/models/Text.py
materialize_threats/mx/models/UserObject.py
materialize_threats/mx/models/__init__.py
materialize_threats/mx/shapes/Arguments.py
materialize_threats/mx/shapes/CoordsTranslate.py
materialize_threats/mx/shapes/DotAttr.py
materialize_threats/mx/shapes/Rect.py
materialize_threats/mx/shapes/__init__.py
materialize_threats/mx/utils/MxConst.py
materialize_threats/mx/utils/MxUtils.py
materialize_threats/mx/utils/__init__.py
materialize_threats/mx/utils/deflatedecompress.py
materialize_threats_nathan-1.0.0.dist-info/LICENSE
materialize_threats_nathan-1.0.0.dist-info/METADATA
materialize_threats_nathan-1.0.0.dist-info/WHEEL
materialize_threats_nathan-1.0.0.dist-info/entry_points.txt
materialize_threats_nathan-1.0.0.dist-info/top_level.txt
materialize_threats_nathan-1.0.0.dist-info/RECORD
