Metadata-Version: 2.1
Name: materialize-threats-nathan
Version: 1.0.0
Summary: Copy of secmerc's materialize threats to test pypi publishing
Home-page: https://github.com/sfc-gh-nsfard/materialize-threats
Author: Nathan Sfard
Author-email: author@example.com
License: UNKNOWN
Platform: UNKNOWN
Classifier: Programming Language :: Python :: 3
Classifier: License :: OSI Approved :: Apache Software License
Classifier: Operating System :: OS Independent
Requires-Python: >=3.6
Requires-Dist: peewee
Requires-Dist: gherkin-official
Requires-Dist: pytest
